Metadata-Version: 1.1
Name: tele-bot
Version: 0.0.1
Summary: Telegram bot
Home-page: UNKNOWN
Author: rocailler
Author-email: rocailler@gmail.com
License: MIT
Keywords: telegram
Platform: UNKNOWN
Classifier: Development Status :: 5 - Production/Stable
Classifier: Intended Audience :: Education
Classifier: Operating System :: Microsoft :: Windows :: Windows 10
Classifier: License :: OSI Approved :: MIT License
Classifier: Programming Language :: Python :: 3
